PittAPI/__init__.py
PittAPI/course.py
PittAPI/dining.py
PittAPI/lab.py
PittAPI/laundry.py
PittAPI/library.py
PittAPI/news.py
PittAPI/people.py
PittAPI/shuttle.py
PittAPI/status.py
PittAPI/textbook.py
PittAPI-0.2.6.dist-info/LICENSE
PittAPI-0.2.6.dist-info/METADATA
PittAPI-0.2.6.dist-info/WHEEL
PittAPI-0.2.6.dist-info/top_level.txt
PittAPI-0.2.6.dist-info/RECORD
