Metadata-Version: 2.1
Name: PittAPI
Version: 0.2.6
Summary: An API to get data from Pitt and Pitt-related applications.
Home-page: https://github.com/Pitt-CSC/PittAPI
Author: University of Pittsburgh Computer Science Club
Author-email: pittcsc@gmail.com
License: GPLv2
Keywords: api open-data university-of-pittsburgh pittsburgh pitt
Platform: UNKNOWN
Classifier: Development Status :: 4 - Beta
Classifier: Intended Audience :: Developers
Classifier: Topic :: Software Development :: Build Tools
Classifier: License :: OSI Approved :: GNU General Public License v2 (GPLv2)
Classifier: Programming Language :: Python :: 3
Classifier: Programming Language :: Python :: 3.4
Classifier: Programming Language :: Python :: 3.5
Classifier: Programming Language :: Python :: 3.6
Provides-Extra: test
